CHANGES.txt
CONTRIBUTORS.txt
MANIFEST.in
README.txt
setup.cfg
setup.py
docs/LICENSE.LGPL
docs/LICENSE.txt
src/fnord/__init__.py
src/fnord.easycodec.egg-info/PKG-INFO
src/fnord.easycodec.egg-info/SOURCES.txt
src/fnord.easycodec.egg-info/dependency_links.txt
src/fnord.easycodec.egg-info/entry_points.txt
src/fnord.easycodec.egg-info/namespace_packages.txt
src/fnord.easycodec.egg-info/not-zip-safe
src/fnord.easycodec.egg-info/requires.txt
src/fnord.easycodec.egg-info/top_level.txt
src/fnord/easycodec/__init__.py
src/fnord/easycodec/decorators.py
src/fnord/easycodec/factories.py