Metadata-Version: 1.0
Name: fnord.easycodec
Version: 0.2
Summary: Tools to create and register codecs.
Home-page: https://github.com/batlock666/fnord.easycodec
Author: Bert Vanderbauwhede
Author-email: batlock666@gmail.com
License: lgpl
Keywords: codec
Platform: UNKNOWN
Classifier: Programming Language :: Python
Classifier: License :: OSI Approved :: GNU Library or Lesser General Public License (LGPL)
Classifier: Operating System :: OS Independent
Classifier: Programming Language :: Python
Classifier: Topic :: Software Development :: Libraries :: Python Modules
